enderlit_crypto/__init__.py
enderlit_crypto-1.0.2.dist-info/licenses/LICENSE
enderlit_crypto-1.0.2.dist-info/METADATA
enderlit_crypto-1.0.2.dist-info/WHEEL
enderlit_crypto-1.0.2.dist-info/top_level.txt
enderlit_crypto-1.0.2.dist-info/RECORD
