Metadata-Version: 2.4
Name: enderlit_crypto
Version: 1.0.2
Summary: Шифратор-дешифратор от Enderlit
Author: Enderlit
License: MIT
Classifier: Programming Language :: Python :: 3
Classifier: License :: OSI Approved :: MIT License
Classifier: Operating System :: OS Independent
Requires-Python: >=3.6
License-File: LICENSE
Dynamic: author
Dynamic: classifier
Dynamic: description
Dynamic: description-content-type
Dynamic: license
Dynamic: license-file
Dynamic: requires-python
Dynamic: summary
